VulnBox/__init__.py
TP_VulnBox-2024.7.29.dist-info/LICENSE.txt
TP_VulnBox-2024.7.29.dist-info/METADATA
TP_VulnBox-2024.7.29.dist-info/WHEEL
TP_VulnBox-2024.7.29.dist-info/entry_points.txt
TP_VulnBox-2024.7.29.dist-info/top_level.txt
TP_VulnBox-2024.7.29.dist-info/RECORD
