Metadata-Version: 2.1
Name: TP-VulnBox
Version: 2024.7.29
Summary: VulnBox is a container that is intentionally designed with vulnerabilities to allow security professionals to practice and improve their offensive security skills, such as penetration testing and vulnerability assessment.
Home-page: https://github.com/truocphan/TP-VulnBox
Author: TP Cyber Security
Author-email: tpcybersec2023@gmail.com
License: MIT
Platform: UNKNOWN
Classifier: Programming Language :: Python :: 3
Classifier: Programming Language :: Python :: 2
Requires-Dist: certifi
Requires-Dist: charset-normalizer
Requires-Dist: colorama
Requires-Dist: idna
Requires-Dist: requests
Requires-Dist: tqdm
Requires-Dist: urllib3
